AUTHORS
HISTORY
LICENSE
explorer/__init__.py
explorer/actions.py
explorer/admin.py
explorer/app_settings.py
explorer/apps.py
explorer/connections.py
explorer/exporters.py
explorer/forms.py
explorer/migrations/0001_initial.py
explorer/migrations/0002_auto_20150501_1515.py
explorer/migrations/0003_query_snapshot.py
explorer/migrations/0004_querylog_duration.py
explorer/migrations/0005_auto_20160105_2052.py
explorer/migrations/0006_query_connection.py
explorer/migrations/0007_querylog_connection.py
explorer/migrations/0008_auto_20190308_1642.py
explorer/migrations/__init__.py
explorer/models.py
explorer/permissions.py
explorer/schema.py
explorer/static/explorer/bootstrap.min.css
explorer/static/explorer/explorer.css
explorer/static/explorer/explorer.js
explorer/static/explorer/jquery-ui.min.js
explorer/static/explorer/query-list.js
explorer/tasks.py
explorer/templates/explorer/base.html
explorer/templates/explorer/export_buttons.html
explorer/templates/explorer/fullscreen.html
explorer/templates/explorer/params.html
explorer/templates/explorer/pdf_template.html
explorer/templates/explorer/play.html
explorer/templates/explorer/preview_pane.html
explorer/templates/explorer/query.html
explorer/templates/explorer/query_confirm_delete.html
explorer/templates/explorer/query_list.html
explorer/templates/explorer/querylog_list.html
explorer/templates/explorer/schema.html
explorer/templates/explorer/schema_building.html
explorer/templatetags/__init__.py
explorer/templatetags/explorer_tags.py
explorer/tests/__init__.py
explorer/tests/factories.py
explorer/tests/test_actions.py
explorer/tests/test_apps.py
explorer/tests/test_exporters.py
explorer/tests/test_forms.py
explorer/tests/test_models.py
explorer/tests/test_schema.py
explorer/tests/test_tasks.py
explorer/tests/test_utils.py
explorer/tests/test_views.py
explorer/tests/urls.py
explorer/urls.py
explorer/utils.py
explorer/views.py
pancho_sql_explorer-0.1.0.dist-info/LICENSE
pancho_sql_explorer-0.1.0.dist-info/WHEEL
pancho_sql_explorer-0.1.0.dist-info/METADATA
pancho_sql_explorer-0.1.0.dist-info/RECORD
